stave_backend/__init__.py
stave_backend/__version__.py
stave_backend/admin.py
stave_backend/models.py
stave_backend/urls.py
stave_backend/handlers/__init__.py
stave_backend/handlers/crossdoc.py
stave_backend/handlers/document.py
stave_backend/handlers/nlp.py
stave_backend/handlers/project.py
stave_backend/handlers/session.py
stave_backend/handlers/user.py
stave_backend/lib/__init__.py
stave_backend/lib/require_login.py
stave_backend/lib/stave_cli.py
stave_backend/lib/stave_config.py
stave_backend/lib/stave_project.py
stave_backend/lib/stave_session.py
stave_backend/lib/stave_viewer.py
stave_backend/lib/utils.py
stave_backend/lib/build/Petuum.png
stave_backend/lib/build/Stave-dark-text@1x.png
stave_backend/lib/build/Stave-graphic@2x.png
stave_backend/lib/build/Stave-graphic@5x.png
stave_backend/lib/build/asset-manifest.json
stave_backend/lib/build/favicon.ico
stave_backend/lib/build/index.html
stave_backend/lib/build/manifest.json
stave_backend/lib/build/robots.txt
stave_backend/lib/build/static/css/2.adea8d99.chunk.css
stave_backend/lib/build/static/css/2.adea8d99.chunk.css.map
stave_backend/lib/build/static/css/main.62c43e19.chunk.css
stave_backend/lib/build/static/css/main.62c43e19.chunk.css.map
stave_backend/lib/build/static/js/2.6bc0a490.chunk.js
stave_backend/lib/build/static/js/2.6bc0a490.chunk.js.LICENSE.txt
stave_backend/lib/build/static/js/2.6bc0a490.chunk.js.map
stave_backend/lib/build/static/js/main.d8e6e941.chunk.js
stave_backend/lib/build/static/js/main.d8e6e941.chunk.js.map
stave_backend/lib/build/static/js/runtime-main.7cd001e8.js
stave_backend/lib/build/static/js/runtime-main.7cd001e8.js.map
stave_backend/lib/build/static/media/jsoneditor-icons.15f2789d.svg
stave_backend/migrations/0001_initial.py
stave_backend/migrations/0002_document_ontology.py
stave_backend/migrations/0003_auto_20200712_0421.py
stave_backend/migrations/0004_auto_20200712_0957.py
stave_backend/migrations/0005_remove_document_ontology.py
stave-0.0.2.dist-info/LICENSE
stave-0.0.2.dist-info/METADATA
stave-0.0.2.dist-info/WHEEL
stave-0.0.2.dist-info/entry_points.txt
stave-0.0.2.dist-info/top_level.txt
stave-0.0.2.dist-info/RECORD
