Metadata-Version: 2.1
Name: stave
Version: 0.0.2
Summary: Stave is a fast, lightweight, extensible web-based text annotation and visualization tool designed to support a wide range of data types and NLP tasks.
Home-page: https://github.com/asyml/stave
License: Apache License Version 2.0
Platform: any
Classifier: Intended Audience :: Developers
Classifier: Intended Audience :: Education
Classifier: Intended Audience :: Science/Research
Classifier: Operating System :: OS Independent
Classifier: Programming Language :: Python
Classifier: Programming Language :: Python :: 3.6
Classifier: Programming Language :: Python :: 3.7
License-File: LICENSE
Requires-Dist: requests (==2.25.1)
Requires-Dist: django (>=3.0.4)
Requires-Dist: django-guardian (==2.3.0)
Requires-Dist: tornado (==6.1)
Provides-Extra: forte
Requires-Dist: forte ; extra == 'forte'
